JaesonTest/test1.py
JaesonTest/test2.py
JaesonTest-0.0.0.2.dist-info/METADATA
JaesonTest-0.0.0.2.dist-info/WHEEL
JaesonTest-0.0.0.2.dist-info/top_level.txt
JaesonTest-0.0.0.2.dist-info/RECORD
