Metadata-Version: 2.1
Name: JaesonTest
Version: 0.0.0.2
Summary: My First Test Package
Home-page: https://lingua.blog.me/...
Author: JaeHyung Son
Author-email: thswogud02@gmail.com
License: MIT
Platform: UNKNOWN
Requires-Python: >=3
